DevOpsAPI/__init__.py
DevOpsAPI/api.py
DevOpsAPI/base.py
DevOpsAPI/connection.py
DevOpsAPI/projects.py
DevOpsAPI/testing.py
DevOpsAPI/wi.py
DevOpsAPI-0.1.1.dist-info/LICENSE
DevOpsAPI-0.1.1.dist-info/METADATA
DevOpsAPI-0.1.1.dist-info/WHEEL
DevOpsAPI-0.1.1.dist-info/top_level.txt
DevOpsAPI-0.1.1.dist-info/RECORD
