Metadata-Version: 2.1
Name: DevOpsAPI
Version: 0.1.1
Summary: A simple object-oriented python interface to the DevOps REST API
Author-email: Claudio Klingler <ck@realtime-projects.com>
Project-URL: Homepage, https://github.com/acre-bdd/DevOpsAPI
Project-URL: Bug Tracker, https://github.com/acre-bdd/DevOpsAPI/issues
Classifier: Programming Language :: Python :: 3
Classifier: License :: OSI Approved :: MIT License
Classifier: Operating System :: OS Independent
Requires-Python: >=3.7
License-File: LICENSE
Requires-Dist: lxml
Requires-Dist: requests
